gddl/__init__.py
gddl/__main__.py
gddl/downloaders.py
gddl/gddl.py
gddl/utils.py
gddl-0.1.5.dist-info/LICENSE
gddl-0.1.5.dist-info/METADATA
gddl-0.1.5.dist-info/WHEEL
gddl-0.1.5.dist-info/entry_points.txt
gddl-0.1.5.dist-info/top_level.txt
gddl-0.1.5.dist-info/RECORD
