Metadata-Version: 2.1
Name: gddl
Version: 0.1.5
Summary: Download files from google drive with resuming capability.
Home-page: https://github.com/rafiibrahim8/gddl
Author: Ibrahim Rafi
Author-email: me@ibrahimrafi.me
License: MIT
Download-URL: https://github.com/rafiibrahim8/gddl/archive/v0.1.5.tar.gz
Keywords: gddl,downloader,drive,google
Platform: any
Classifier: Development Status :: 3 - Alpha
Classifier: Intended Audience :: End Users/Desktop
Classifier: Topic :: Utilities
Classifier: Topic :: Internet
Classifier: License :: OSI Approved :: MIT License
Classifier: Programming Language :: Python :: 3
Classifier: Programming Language :: Python :: 3.4
Classifier: Programming Language :: Python :: 3.5
Classifier: Programming Language :: Python :: 3.6
Classifier: Programming Language :: Python :: 3.7
Classifier: Programming Language :: Python :: 3.8
Classifier: Programming Language :: Python :: 3.9
Requires-Dist: requests
Requires-Dist: urllib3
